jkexcel/__init__.py
jkexcel/core/application.py
jkexcel/core/excel_driver.py
jkexcel/core/range.py
jkexcel/core/workbook.py
jkexcel/core/workbooks.py
jkexcel/core/worksheet.py
jkexcel/core/worksheets.py
jkexcel/models/config.py
jkexcel/models/enums.py
jkexcel/models/exceptions.py
jkexcel/operations/data_operations.py
jkexcel/operations/format_operations.py
jkexcel/utils/helpers.py
jkexcel/utils/validators.py
jkexcel-0.1.5.dist-info/licenses/LICENSE
jkexcel-0.1.5.dist-info/METADATA
jkexcel-0.1.5.dist-info/WHEEL
jkexcel-0.1.5.dist-info/top_level.txt
jkexcel-0.1.5.dist-info/RECORD
