Metadata-Version: 2.4
Name: jkexcel
Version: 0.1.5
Summary: A Python library for Excel operations using COM interface
Author-email: Mokiru <694896250@qq.com>
License: MIT
Project-URL: Homepage, https://github.com/Mokiru/jkexcel
Project-URL: Repository, https://github.com/Mokiru/jkexcel
Classifier: Development Status :: 3 - Alpha
Classifier: Intended Audience :: Developers
Classifier: License :: OSI Approved :: MIT License
Classifier: Operating System :: Microsoft :: Windows
Classifier: Programming Language :: Python :: 3
Classifier: Programming Language :: Python :: 3.7
Classifier: Programming Language :: Python :: 3.8
Classifier: Programming Language :: Python :: 3.9
Classifier: Programming Language :: Python :: 3.10
Classifier: Programming Language :: Python :: 3.11
Requires-Python: >=3.7
License-File: LICENSE
Requires-Dist: pywin32>=311
Requires-Dist: psutil>=7.2.0
Requires-Dist: pandas
Dynamic: license-file
